gishndev_demo/__init__.py
gishndev_demo/common.py
gishndev_demo/gishndev_demo.py
gishndev_demo-0.0.2.dist-info/LICENSE
gishndev_demo-0.0.2.dist-info/METADATA
gishndev_demo-0.0.2.dist-info/WHEEL
gishndev_demo-0.0.2.dist-info/top_level.txt
gishndev_demo-0.0.2.dist-info/RECORD
