Metadata-Version: 2.2
Name: gishndev-demo
Version: 0.0.2
Summary: Package for test the creation of python packages
Home-page: https://github.com/lalgonzales/gishndev-demo
Author: Luis López
Author-email: lalgonzales@gmail.com
License: MIT license
Keywords: gishndev_demo
Classifier: Intended Audience :: Developers
Classifier: License :: OSI Approved :: MIT License
Classifier: Natural Language :: English
Classifier: Programming Language :: Python :: 3
Classifier: Programming Language :: Python :: 3.8
Classifier: Programming Language :: Python :: 3.9
Classifier: Programming Language :: Python :: 3.10
Classifier: Programming Language :: Python :: 3.11
Requires-Python: >=3.8
License-File: LICENSE
Dynamic: author
Dynamic: author-email
Dynamic: classifier
Dynamic: description
Dynamic: description-content-type
Dynamic: home-page
Dynamic: keywords
Dynamic: license
Dynamic: requires-python
Dynamic: summary
